sit4onnx/__init__.py
sit4onnx/__main__.py
sit4onnx/onnx_inference_test.py
sit4onnx-1.0.10.dist-info/licenses/LICENSE
sit4onnx-1.0.10.dist-info/METADATA
sit4onnx-1.0.10.dist-info/WHEEL
sit4onnx-1.0.10.dist-info/entry_points.txt
sit4onnx-1.0.10.dist-info/top_level.txt
sit4onnx-1.0.10.dist-info/RECORD
